aws_cost_optimization_6/__init__.py
aws_cost_optimization_6/_ec2_costing.py
aws_cost_optimization_6/_rds_costing.py
aws_cost_optimization_6/_ri_recommendations.py
aws_cost_optimization_6/_savings_plan.py
aws_cost_optimization_6/utils.py
aws_cost_optimization_6-0.2.0.dist-info/LICENCE
aws_cost_optimization_6-0.2.0.dist-info/METADATA
aws_cost_optimization_6-0.2.0.dist-info/WHEEL
aws_cost_optimization_6-0.2.0.dist-info/top_level.txt
aws_cost_optimization_6-0.2.0.dist-info/RECORD
